MANIFEST.in
README.md
license.txt
setup.py
parledata/__init__.py
parledata/args.py
parledata/data.py
parledata/init.py
parledata/log.py
parledata/media.py
parledata/misc.py
parledata/pld.py
parledata/scan.py
parledata/template.py
parledata.egg-info/PKG-INFO
parledata.egg-info/SOURCES.txt
parledata.egg-info/dependency_links.txt
parledata.egg-info/entry_points.txt
parledata.egg-info/top_level.txt