Metadata-Version: 1.1
Name: parledata
Version: 0.5
Summary: Parle Data - little gateway from hd to json
Home-page: http://github.com/parleweb/parledata
Author: Emmanuel Sandorfi
Author-email: e.sandorfi@parleweb.com
License: WTFPL
Platform: UNKNOWN
Classifier: Programming Language :: Python
Classifier: Development Status :: 1 - Planning
Classifier: License :: OSI Approved
Classifier: Natural Language :: French
Classifier: Operating System :: OS Independent
Classifier: Programming Language :: Python :: 3.6
Classifier: Topic :: Communications
